io_helper/__init__.py
io_helper/io_helper.py
io_helper-0.2.5.dist-info/DESCRIPTION.rst
io_helper-0.2.5.dist-info/METADATA
io_helper-0.2.5.dist-info/RECORD
io_helper-0.2.5.dist-info/WHEEL
io_helper-0.2.5.dist-info/metadata.json
io_helper-0.2.5.dist-info/top_level.txt
